aef_nattanon_py/__init__.py
aef_nattanon_py/detector.py
aef_nattanon_py/multiplication.py
aef_nattanon_py/yolov3detector.py
aef_nattanon_py/files/coco.names
aef_nattanon_py/files/yolov3-tiny.cfg
aef_nattanon_py/files/yolov3-tiny.weights
aef_nattanon_py-0.2.3.dist-info/METADATA
aef_nattanon_py-0.2.3.dist-info/WHEEL
aef_nattanon_py-0.2.3.dist-info/top_level.txt
aef_nattanon_py-0.2.3.dist-info/RECORD
